{
  "kind": "feature_evidence_report",
  "features": [
    {
      "featureId": "feature-add-a-mission-log-history-view-in-the-frontend-that-displays-all-automated-daily-log-entries-with-date-completed-activities-and-rewards-earned",
      "featureTitle": "Add a mission log history view in the frontend that displays all automated daily log entries with date, completed activities, and rewards earned",
      "files": [
        "frontend/src/App.tsx",
        "frontend/src/components/layout/AppLayout.tsx",
        "frontend/src/content/copy.ts",
        "frontend/src/pages/MissionLogPage.tsx"
      ],
      "components": [
        "authorization@4.0.0",
        "core-infrastructure@1.0.2",
        "shadcn-ui@1.0.0",
        "build-template-react@1.0.0",
        "initial-app@1.0.0",
        "github-export-icp-cli@1.0.0"
      ],
      "testIds": [
        "REQ-3"
      ],
      "confidence": "high"
    }
  ]
}